jackal_tools/__init__.py
jackal_tools/sniffer.py
jackal_tools-0.0.3.dist-info/DESCRIPTION.rst
jackal_tools-0.0.3.dist-info/METADATA
jackal_tools-0.0.3.dist-info/RECORD
jackal_tools-0.0.3.dist-info/WHEEL
jackal_tools-0.0.3.dist-info/entry_points.txt
jackal_tools-0.0.3.dist-info/metadata.json
jackal_tools-0.0.3.dist-info/top_level.txt
